makegit/__init__.py
makegit/__main__.py
makegit/main/__init__.py
makegit/main/exceptions.py
makegit/main/gitconfig.py
makegit/main/makegit.py
makegit/main/system_execute.py
makegit/main/validators.py
makegit-0.80.2.dist-info/METADATA
makegit-0.80.2.dist-info/WHEEL
makegit-0.80.2.dist-info/top_level.txt
makegit-0.80.2.dist-info/RECORD
