Metadata-Version: 2.1
Name: makegit
Version: 0.80.2
Summary: Merge GIT submodule repositories into a single buildrepo
Home-page: https://github.com/LINKIT-Group/makegit
Author: Anthony Potappel
Author-email: anthony.potappel@gmail.com
License: UNKNOWN
Platform: UNKNOWN
Classifier: Operating System :: POSIX :: Linux
Classifier: License :: OSI Approved :: MIT License
Classifier: Programming Language :: Python :: 3.5
Classifier: Programming Language :: Python :: 3.6
Classifier: Programming Language :: Python :: 3.7
